__init__.py
chorusReports.py
chorusReports-0.0.11.dist-info/LICENSE
chorusReports-0.0.11.dist-info/METADATA
chorusReports-0.0.11.dist-info/WHEEL
chorusReports-0.0.11.dist-info/top_level.txt
chorusReports-0.0.11.dist-info/RECORD
